sigma/backends/panther/__init__.py
sigma/backends/panther/helpers/base.py
sigma/backends/panther/helpers/pantherflow_helper.py
sigma/backends/panther/helpers/python_helper.py
sigma/backends/panther/helpers/sdyaml_helper.py
sigma/backends/panther/panther_backend.py
sigma/pipelines/panther/__init__.py
sigma/pipelines/panther/carbon_black_panther_pipeline.py
sigma/pipelines/panther/crowdstrike_panther_pipeline.py
sigma/pipelines/panther/panther_pipeline.py
sigma/pipelines/panther/processing.py
sigma/pipelines/panther/replace_condition_ends_with.py
sigma/pipelines/panther/sdyaml_transformation.py
sigma/pipelines/panther/sentinelone_panther_pipeline.py
sigma/pipelines/panther/sysmon_panther_pipeline.py
sigma/pipelines/panther/windows_panther_pipeline.py
pysigma_backend_panther-0.2.9.dist-info/LICENSE
pysigma_backend_panther-0.2.9.dist-info/METADATA
pysigma_backend_panther-0.2.9.dist-info/WHEEL
pysigma_backend_panther-0.2.9.dist-info/RECORD
