Metadata-Version: 2.3
Name: pySigma-backend-panther
Version: 0.2.9
Summary: pySigma backend for Panther
License: LGPL-3.0-only
Author: Panther Labs Inc
Author-email: pypi@runpanther.io
Maintainer: Panther Labs Inc
Maintainer-email: pypi@runpanther.io
Requires-Python: >=3.9,<4.0
Classifier: License :: OSI Approved :: GNU Lesser General Public License v3 (LGPLv3)
Classifier: Programming Language :: Python :: 3
Classifier: Programming Language :: Python :: 3.9
Classifier: Programming Language :: Python :: 3.10
Classifier: Programming Language :: Python :: 3.11
Classifier: Programming Language :: Python :: 3.12
Classifier: Programming Language :: Python :: 3.13
Requires-Dist: black (>=24.3.0,<25.0.0)
Requires-Dist: defusedxml (>=0.7.1,<0.8.0)
Requires-Dist: pysigma (>=0.11.19,<0.12.0)
Project-URL: Repository, https://github.com/panther-labs/pySigma-backend-panther
